flexprice/__init__.py
flexprice/api_client.py
flexprice/api_response.py
flexprice/async_utils.py
flexprice/configuration.py
flexprice/exceptions.py
flexprice/py.typed
flexprice/rest.py
flexprice/api/__init__.py
flexprice/api/addons_api.py
flexprice/api/auth_api.py
flexprice/api/connections_api.py
flexprice/api/cost_sheets_api.py
flexprice/api/coupons_api.py
flexprice/api/credit_grants_api.py
flexprice/api/credit_notes_api.py
flexprice/api/customers_api.py
flexprice/api/entitlements_api.py
flexprice/api/entity_integration_mappings_api.py
flexprice/api/environments_api.py
flexprice/api/events_api.py
flexprice/api/features_api.py
flexprice/api/integration_api.py
flexprice/api/integrations_api.py
flexprice/api/invoices_api.py
flexprice/api/payments_api.py
flexprice/api/plans_api.py
flexprice/api/price_units_api.py
flexprice/api/prices_api.py
flexprice/api/secrets_api.py
flexprice/api/subscriptions_api.py
flexprice/api/tasks_api.py
flexprice/api/tax_associations_api.py
flexprice/api/tax_rates_api.py
flexprice/api/tenants_api.py
flexprice/api/users_api.py
flexprice/api/wallets_api.py
flexprice/api/webhooks_api.py
flexprice/models/__init__.py
flexprice/models/coupon_association_coupon_association.py
flexprice/models/coupon_coupon.py
flexprice/models/creditnote_credit_note_line_item.py
flexprice/models/customer_customer.py
flexprice/models/dto_add_addon_to_subscription_request.py
flexprice/models/dto_add_schedule_phase_request.py
flexprice/models/dto_addon_association_response.py
flexprice/models/dto_addon_response.py
flexprice/models/dto_address.py
flexprice/models/dto_aggregated_entitlement.py
flexprice/models/dto_aggregated_feature.py
flexprice/models/dto_alert_config.py
flexprice/models/dto_auth_response.py
flexprice/models/dto_billing_cycle_info.py
flexprice/models/dto_billing_period_info.py
flexprice/models/dto_bulk_ingest_event_request.py
flexprice/models/dto_calculate_roi_request.py
flexprice/models/dto_cancel_subscription_request.py
flexprice-1.0.28.dist-info/METADATA
flexprice-1.0.28.dist-info/WHEEL
flexprice-1.0.28.dist-info/top_level.txt
flexprice-1.0.28.dist-info/RECORD
