Metadata-Version: 2.4
Name: flexprice
Version: 1.0.28
Summary: Official FlexPrice Python SDK
Home-page: https://github.com/flexprice/python-sdk
Author: FlexPrice Team
Author-email: tech@flexprice.io
Project-URL: Source, https://github.com/flexprice/python-sdk
Project-URL: Documentation, https://docs.flexprice.io
Project-URL: Bug Tracker, https://github.com/flexprice/python-sdk/issues
Keywords: FlexPrice,Pricing,API,SDK,FlexPrice API
Classifier: Development Status :: 4 - Beta
Classifier: Intended Audience :: Developers
Classifier: Programming Language :: Python :: 3
Classifier: Programming Language :: Python :: 3.8
Classifier: Programming Language :: Python :: 3.9
Classifier: Programming Language :: Python :: 3.10
Classifier: Programming Language :: Python :: 3.11
Classifier: License :: OSI Approved :: MIT License
Classifier: Operating System :: OS Independent
Requires-Python: >= 3.8
Requires-Dist: urllib3<3.0.0,>=2.0.0
Requires-Dist: python-dateutil>=2.8.2
Requires-Dist: pydantic>=2
Requires-Dist: typing-extensions>=4.7.1
Dynamic: author
Dynamic: author-email
Dynamic: classifier
Dynamic: description
Dynamic: description-content-type
Dynamic: home-page
Dynamic: keywords
Dynamic: project-url
Dynamic: requires-dist
Dynamic: requires-python
Dynamic: summary
